README.rst
setup.py
clerk/__init__.py
clerk/cli.py
clerk/ext_csv.py
clerk/ext_json.py
clerk/maps.py
clerk/scdb.py
clerk/scores.py
clerk/utils.py
nyt_clerk.egg-info/PKG-INFO
nyt_clerk.egg-info/SOURCES.txt
nyt_clerk.egg-info/dependency_links.txt
nyt_clerk.egg-info/entry_points.txt
nyt_clerk.egg-info/requires.txt
nyt_clerk.egg-info/top_level.txt