Metadata-Version: 1.1
Name: nyt-clerk
Version: 0.1.18
Summary: Python client for parsing SCOTUS data from multiple sources.
Home-page: https://github.com/newsdev/nyt-clerk
Author: Jeremy Bowers
Author-email: jeremy.bowers@nytimes.com
License: Apache License 2.0
Keywords: SCOTUS data parsing scraping legal law court
Platform: UNKNOWN
Classifier: Development Status :: 3 - Alpha
Classifier: Intended Audience :: Developers
Classifier: Programming Language :: Python
Classifier: Topic :: Software Development :: Libraries :: Python Modules
